setup.cfg
setup.py
examples/__init__.py
examples/engine.py
examples/0_init/__init__.py
examples/0_init/pong.py
interactive_python/__init__.py
interactive_python/_util.py
interactive_python/connection.py
interactive_python/discovery.py
interactive_python/encoding.py
interactive_python/errors.py
interactive_python/keycodes.py
interactive_python/log.py
interactive_python/oauth.py
interactive_python/scene.py
interactive_python/state.py
interactive_python.egg-info/PKG-INFO
interactive_python.egg-info/SOURCES.txt
interactive_python.egg-info/dependency_links.txt
interactive_python.egg-info/requires.txt
interactive_python.egg-info/top_level.txt